Computer_Architecture/full_adder/f_adder.v
module f_adder (a, b, cry, sum, cin);// module module_name(input, output)
    input a, b, cin;
    output cry, sum;
    wire s1,c1,c2;
    
    xor xor1(s1, a, b);
    and and1(c1, a, b);
    xor xor2(sum,s1,cin);
    and a2(c2,s1,cin);
    or or1(carry,c1,c2);
endmodule

Computer_Architecture/full_adder/f_adder_tb.v
`include "f_adder.v"
module f_adder_tb;
    reg a, b, cin;
    wire cry, sum;
    //f_adder f1 (a, b, cin, sum, cry);//module call
    initial begin
        $dumpfile("f_adder.vcd");
        $dumpvars(0,f_adder_tb);
        a = 0;
        b = 0;
        cin= 0;
        #1
        a = 0;
        b = 0;
        cin= 1;
        #1
        a = 0;
        b = 1;
        cin=0;
        #1
        a = 0;
        b = 1;
        cin=1;
        #1
        a= 1;
        b=0;
        cin=0;
        #1
        a = 1;
        b = 0;
        cin=1;
        #1
        a = 1;
        b = 1;
        cin=0;
        #1
        a= 1;
        b= 1;
        cin=1;
    end
endmodule

Computer_Architecture/full_adder/f_adder.vcd
$date
	Thu Dec 01 17:21:59 2022
$end
$version
	Icarus Verilog
$end
$timescale
	1s
$end
$scope module f_adder_tb $end
$var reg 1 ! a $end
$var reg 1 " b $end
$var reg 1 # cin $end
$upscope $end
$enddefinitions $end
#0
$dumpvars
0#
0"
0!
$end
#1
1#
#2
0#
1"
#3
1#
#4
0#
0"
1!
#5
1#
#6
0#
1"
#7
1#
